{
    "atividade legislativa": "projeto de lei n 182 de 2024",
    "autoria": "câmara dos deputados",
    "iniciativa": "deputado federal jaime martins psd/mg",
    "ementa": "institui o sistema brasileiro de comércio de emissões de gases de efeito estufa sbce e altera as leis ns 12187 de 29 de dezembro de 2009 12651 de 25 de maio de 2012 código florestal 6385 de 7 de dezembro de 1976 11033 de 21 de dezembro de 2004 e 6015 de 31 de dezembro de 1973 lei de registros públicos",
    "assunto": "economia e desenvolvimento   sistema financeiro nacional",
    "despacho": "04/11/2024 decisão da presidência ao plenário sfplen plenário do senado federal",
    "relatoria": "plen  plenário do senado federal relatores senadora leila barros encerrado em 13/11/2024  matéria deliberada no plenário",
    "tramitação encerrada": {
        "decisão": "aprovada pelo plenário",
        "destino": "à câmara dos deputados",
        "último local": "26/11/2024  secretaria de expediente",
        "último estado": "12/12/2024  transformada em norma jurídica"
    },
    "tramitação": [
        {
            "data": "12/12/2024",
            "órgão": "sfsexpe  secretaria de expediente",
            "situação": "transformada em norma jurídica",
            "ação": "pr presidência da república sancionada lei 15042 de 2024 dou diário oficial da união  12/12/2024  seção i  págs 4 e 8 sancionada em 11/12/2024"
        },
        {
            "data": "26/11/2024",
            "órgão": "plen  plenário do senado federal",
            "situação": null,
            "ação": "encaminhado à publicação o ofício da câmara dos deputados n 603 de 2024 na origem que comunica o envio à sanção do projeto de lei n 182 de 2024 a matéria vai à secretaria de expediente ação"
        },
        {
            "data": "19/11/2024",
            "órgão": "sfsexpe  secretaria de expediente",
            "situação": "remetida à câmara dos deputados",
            "ação": "remetido ofício sf n 1291 de 18/11/24 ao senhor primeirosecretário da câmara dos deputados comunicando que o senado federal aprovou em revisão nos termos do substitutivo o projeto"
        },
        {
            "data": "19/11/2024",
            "órgão": "sfsexpe  secretaria de expediente",
            "situação": null,
            "ação": "anexado o texto revisado ação"
        },
        {
            "data": "13/11/2024",
            "órgão": "plen  plenário do senado federal",
            "situação": "aprovado o substitutivo",
            "ação": "continuação da sessão deliberativa ordinária iniciada em 12/11/2024 encaminhadas à publicação as emendas ns 52 a 58 encaminhado à publicação o parecer n 186 de 2024plen/sf proferido pela senadora leila barros o qual é favorável ao projeto e pelo acolhimento total ou parcial das emendas ns 2 8 11 13 14 15 20 24 27 35 36 38 39 40 41 42 45 47 49 52 54 55 56 57 e 58 na forma da emenda n 59 substitutivo que apresenta complementada com os acolhimentos de plenário e pela rejeição das demais emendas prejudicados os requerimentos ns 745 e 765 de 2024 tendo em vista  respectivamente  os acolhimentos parciais das emendas ns 8 e 42 encaminhado à publicação  e prejudicado  o requerimento n 781 de 2024 tendo em vista o acolhimento da emenda n 57 retirado o requerimento n 768 de 2024 encaminhado à publicação  e retirado  o requerimento n 779 de 2024 deferido o requerimento n 772 de 2024 de destaque para votação em separado da emenda n 25 encaminhado à publicação  e deferido  o requerimento n 782 de 2024 de destaque para votação em separado da emenda n 58 encerrada a discussão da matéria"
        },
        {
            "data": "13/11/2024",
            "órgão": "plen  plenário do senado federal",
            "situação": null,
            "ação": "recebido o requerimento n 782 de 2024 da liderança do união de destaque para votação em separado da emenda n 58 ação"
        },
        {
            "data": "13/11/2024",
            "órgão": "plen  plenário do senado federal",
            "situação": null,
            "ação": "recebida a emenda n 58 do senador alan rick ação"
        },
        {
            "data": "13/11/2024",
            "órgão": "plen  plenário do senado federal",
            "situação": null,
            "ação": "recebidos da liderança do pl os requerimentos  n 780/2024 de retirada do requerimento n 767  n 781/2024 de destaque para votação em separado da emenda n 57 ação"
        },
        {
            "data": "13/11/2024",
            "órgão": "plen  plenário do senado federal",
            "situação": null,
            "ação": "recebido o requerimento n 779 de 2024 da liderança do republicanos de destaque para votação em separado da emenda n 26 ação"
        },
        {
            "data": "13/11/2024",
            "órgão": "plen  plenário do senado federal",
            "situação": null,
            "ação": "recebido o relatório da senadora leila barros ação"
        },
        {
            "data": "13/11/2024",
            "órgão": "plen  plenário do senado federal",
            "situação": null,
            "ação": "recebida a emenda n 57 do marcos rogério ação"
        },
        {
            "data": "13/11/2024",
            "órgão": "plen  plenário do senado federal",
            "situação": null,
            "ação": "recebida a emenda n 56 do luis carlos heinze ação"
        },
        {
            "data": "13/11/2024",
            "órgão": "plen  plenário do senado federal",
            "situação": null,
            "ação": "recebida a emenda n 55 do senador carlos portinho ação pg 3 atividade legislativa projeto de lei n 182 de 2024 tramitação"
        },
        {
            "data": "13/11/2024",
            "órgão": "plen  plenário do senado federal",
            "situação": null,
            "ação": "recebida a emenda n 54 do senador alan rick ação"
        },
        {
            "data": "13/11/2024",
            "órgão": "plen  plenário do senado federal",
            "situação": null,
            "ação": "recebida a emenda n 53 do senador izalci lucas ação"
        },
        {
            "data": "13/11/2024",
            "órgão": "plen  plenário do senado federal",
            "situação": null,
            "ação": "recebida a emenda n 52 do senador efraim filho ação"
        },
        {
            "data": "12/11/2024",
            "órgão": "plen  plenário do senado federal",
            "situação": null,
            "ação": "incluído em ordem do dia da continuação da sessão deliberativa ordinária de 12/11/2024 a ser realizada em 13/11/2024 às 14h ação publicado no dsf páginas 12  dsf n 192"
        },
        {
            "data": "12/11/2024",
            "órgão": "plen  plenário do senado federal",
            "situação": null,
            "ação": "sessão deliberativa ordinária  realizada em 12/11/2024 encaminhadas à publicação as emendas ns 25 a 51 retirado pelo primeiro signatário senador carlos portinho o rqs n 769/24 que solicita a extinção de urgência da matéria apreciação adiada encaminhados à publicação os requerimento ns 769/24 765/24 766/24 767/24 768/24 770/24 e 772/24 ação publicado no dsf páginas 134197  dsf n 194 publicado no dsf páginas 51  dsf n 194"
        },
        {
            "data": "12/11/2024",
            "órgão": "plen  plenário do senado federal",
            "situação": null,
            "ação": "recebido o requerimento n 772 de 2024 da liderança do pp de destaque para votação em separado da emenda n 25 ação"
        },
        {
            "data": "12/11/2024",
            "órgão": "plen  plenário do senado federal",
            "situação": null,
            "ação": "recebido o relatório da senadora leila barros ação"
        },
        {
            "data": "12/11/2024",
            "órgão": "plen  plenário do senado federal",
            "situação": null,
            "ação": "recebido o requerimento n 770 de 2024 da liderança do pp de destaque para votação em separado da emenda n 25 ação"
        },
        {
            "data": "12/11/2024",
            "órgão": "plen  plenário do senado federal",
            "situação": null,
            "ação": "recebido o requerimento n 769 de 2024 de líderes solicitando a extinção da urgência para a matéria ação"
        },
        {
            "data": "12/11/2024",
            "órgão": "plen  plenário do senado federal",
            "situação": null,
            "ação": "recebido o requerimento n 768 de 2024 da liderança do podemos de destaque para votação em separado da emenda n 50 ação pg 4 atividade legislativa projeto de lei n 182 de 2024 tramitação"
        },
        {
            "data": "12/11/2024",
            "órgão": "plen  plenário do senado federal",
            "situação": null,
            "ação": "recebida a emenda n 51 do senador carlos portinho ação"
        },
        {
            "data": "12/11/2024",
            "órgão": "plen  plenário do senado federal",
            "situação": null,
            "ação": "recebidos da liderança do pl os requerimentos  n 765/2024 de destaque para votação em separado da emenda n 42  n 766/2024 de retirada dos requerimentos ns 747 e 748 de 2024 e  n 767/2024 de destaque para votação em separado da emenda n 43 ação"
        },
        {
            "data": "12/11/2024",
            "órgão": "plen  plenário do senado federal",
            "situação": null,
            "ação": "recebida a emenda n 50 da senadora soraya thronicke ação"
        },
        {
            "data": "12/11/2024",
            "órgão": "plen  plenário do senado federal",
            "situação": null,
            "ação": "recebida a emenda n 49 do senador dr hiran ação"
        },
        {
            "data": "12/11/2024",
            "órgão": "plen  plenário do senado federal",
            "situação": null,
            "ação": "recebidas as emendas ns 47e 48 do senador mecias de jesus ação"
        },
        {
            "data": "12/11/2024",
            "órgão": "plen  plenário do senado federal",
            "situação": null,
            "ação": "recebidas as emendas ns 44 45 e 46 do senador carlos portinho ação"
        },
        {
            "data": "12/11/2024",
            "órgão": "plen  plenário do senado federal",
            "situação": null,
            "ação": "recebida a emenda n 43 do senador marcos rogério ação"
        },
        {
            "data": "12/11/2024",
            "órgão": "plen  plenário do senado federal",
            "situação": null,
            "ação": "recebida a emenda n 42 do senador rogério marinho ação"
        },
        {
            "data": "12/11/2024",
            "órgão": "plen  plenário do senado federal",
            "situação": null,
            "ação": "recebida a emenda n 41 do senador alan rick ação"
        },
        {
            "data": "12/11/2024",
            "órgão": "plen  plenário do senado federal",
            "situação": null,
            "ação": "recebida a emenda n 40 do senador jayme campos ação"
        },
        {
            "data": "12/11/2024",
            "órgão": "plen  plenário do senado federal",
            "situação": null,
            "ação": "recebidas as emendas n  38 e 39 do senador nelsinho trad ação pg 5 atividade legislativa projeto de lei n 182 de 2024 tramitação"
        },
        {
            "data": "12/11/2024",
            "órgão": "plen  plenário do senado federal",
            "situação": null,
            "ação": "recebida a emenda n 37 do senador zequinha marinho ação"
        },
        {
            "data": "12/11/2024",
            "órgão": "plen  plenário do senado federal",
            "situação": null,
            "ação": "recebida a emenda n 36 do senador efraim filho ação"
        },
        {
            "data": "11/11/2024",
            "órgão": "plen  plenário do senado federal",
            "situação": null,
            "ação": "recebido novo relatório da senadora leila barros ação"
        },
        {
            "data": "11/11/2024",
            "órgão": "plen  plenário do senado federal",
            "situação": null,
            "ação": "recebida a emenda n 35 do senador laércio oliveira ação"
        },
        {
            "data": "11/11/2024",
            "órgão": "plen  plenário do senado federal",
            "situação": null,
            "ação": "recebidas as emendas ns 33 e 34 da senadora soraya thronicke ação"
        },
        {
            "data": "11/11/2024",
            "órgão": "plen  plenário do senado federal",
            "situação": null,
            "ação": "recebidas as emendas ns 30 a 32 do senador zequinha marinho ação"
        },
        {
            "data": "11/11/2024",
            "órgão": "plen  plenário do senado federal",
            "situação": null,
            "ação": "recebida a emenda n 29 do senador jaime bagattoli ação"
        },
        {
            "data": "11/11/2024",
            "órgão": "plen  plenário do senado federal",
            "situação": null,
            "ação": "recebida a emenda n 28 do senador esperidião amin ação"
        },
        {
            "data": "11/11/2024",
            "órgão": "plen  plenário do senado federal",
            "situação": null,
            "ação": "recebida a emenda n 27 do senador efraim filho ação"
        },
        {
            "data": "11/11/2024",
            "órgão": "plen  plenário do senado federal",
            "situação": null,
            "ação": "recebida a emenda n 26 do senador veneziano vital do rêgo ação"
        },
        {
            "data": "10/11/2024",
            "órgão": "plen  plenário do senado federal",
            "situação": null,
            "ação": "incluído em ordem do dia da sessão deliberativa ordinária de 12/11/2024 discussão em turno único matéria tramita em regime de urgência nos termos do requerimento n 743 de 2024 ação pg 6 atividade legislativa projeto de lei n 182 de 2024 tramitação"
        },
        {
            "data": "05/11/2024",
            "órgão": "plen  plenário do senado federal",
            "situação": null,
            "ação": "encaminhado à publicação o rqs n 750 de 2024 do senador esperidião amin de retirada em caráter definitivo da emenda n 22 apresentada ao presente projeto a presidência defere o requerimento ação publicado no dsf páginas 162164  dsf n 191"
        },
        {
            "data": "05/11/2024",
            "órgão": "plen  plenário do senado federal",
            "situação": null,
            "ação": "recebida a emenda n 25 do senador esperidião amin ação"
        },
        {
            "data": "05/11/2024",
            "órgão": "plen  plenário do senado federal",
            "situação": null,
            "ação": "recebido o requerimento n 750 de 2024 do senador esperidião amin solicitando a retirada definitiva da emenda n 22 ação publicado no dsf páginas 162163  dsf n 191"
        },
        {
            "data": "05/11/2024",
            "órgão": "plen  plenário do senado federal",
            "situação": null,
            "ação": "sessão deliberativa extraordinária  semipresencial  realizada em 05/11/2024 encaminhadas à publicação as emendas ns 1 a 24 aprovado o requerimento n 743 de 2024 por meio do qual se solicita urgência para a matéria adiada a apreciação da matéria encaminhados a publicações os requerimentos ns 745 747 e 748 de 2024 de destaques ação publicado no dsf páginas 30100  dsf n 191 publicado no dsf páginas 2023  dsf n 191"
        },
        {
            "data": "05/11/2024",
            "órgão": "plen  plenário do senado federal",
            "situação": null,
            "ação": "recebida a emenda n 24 da senadora professora dorinha seabra ação"
        },
        {
            "data": "05/11/2024",
            "órgão": "plen  plenário do senado federal",
            "situação": null,
            "ação": "recebida a emenda n 23 do senador rogerio marinho ação"
        },
        {
            "data": "05/11/2024",
            "órgão": "plen  plenário do senado federal",
            "situação": null,
            "ação": "recebida a emenda n 22 do senador esperidião amin ação"
        },
        {
            "data": "05/11/2024",
            "órgão": "plen  plenário do senado federal",
            "situação": null,
            "ação": "recebida a emenda n 21 do senador mecias de jesus ação"
        },
        {
            "data": "05/11/2024",
            "órgão": "plen  plenário do senado federal",
            "situação": null,
            "ação": "recebida a emenda n 20 da senadora tereza cristina ação pg 7 atividade legislativa projeto de lei n 182 de 2024 tramitação"
        },
        {
            "data": "05/11/2024",
            "órgão": "plen  plenário do senado federal",
            "situação": null,
            "ação": "recebido o requerimento n 748 de 2024 da liderança do pl de destaque para votação em separado dos 2 e 3 do art 28 do substitutivo da relatora ação publicado no dsf páginas 98100  dsf n 191"
        },
        {
            "data": "05/11/2024",
            "órgão": "plen  plenário do senado federal",
            "situação": null,
            "ação": "recebida a emenda n 19 do senador luis carlos heinze ação"
        },
        {
            "data": "05/11/2024",
            "órgão": "plen  plenário do senado federal",
            "situação": null,
            "ação": "recebido o requerimento n 747 de 2024 da liderança do pl de destaque para votação em separado do art 56 do substitutivo da relatora ação publicado no dsf páginas 9297  dsf n 191"
        },
        {
            "data": "05/11/2024",
            "órgão": "plen  plenário do senado federal",
            "situação": null,
            "ação": "recebida a emenda n 18 do senador luis carlos heinze ação"
        },
        {
            "data": "05/11/2024",
            "órgão": "plen  plenário do senado federal",
            "situação": null,
            "ação": "recebida a emenda n 17 do senador esperidião amin ação"
        },
        {
            "data": "05/11/2024",
            "órgão": "plen  plenário do senado federal",
            "situação": null,
            "ação": "recebida a emenda n 16 do senador castellar neto ação"
        },
        {
            "data": "05/11/2024",
            "órgão": "plen  plenário do senado federal",
            "situação": null,
            "ação": "recebidas as emendas ns 13 a 15 do senador zequinha marinho ação"
        },
        {
            "data": "05/11/2024",
            "órgão": "plen  plenário do senado federal",
            "situação": null,
            "ação": "recebidas as emendas ns 11 e 12 do senador luis carlos heinze ação"
        },
        {
            "data": "05/11/2024",
            "órgão": "plen  plenário do senado federal",
            "situação": null,
            "ação": "recebido o requerimento n 745 de 2024 da liderança do mdb de destaque para votação em separado da emenda n 8 ação publicado no dsf páginas 9091  dsf n 191"
        },
        {
            "data": "05/11/2024",
            "órgão": "plen  plenário do senado federal",
            "situação": null,
            "ação": "recebidas as emendas ns 9 e 10 do senador mecias de jesus ação pg 8 atividade legislativa projeto de lei n 182 de 2024 tramitação"
        },
        {
            "data": "05/11/2024",
            "órgão": "plen  plenário do senado federal",
            "situação": null,
            "ação": "recebida a emenda n 8 do senador eduardo braga ação"
        },
        {
            "data": "05/11/2024",
            "órgão": "plen  plenário do senado federal",
            "situação": null,
            "ação": "recebida a emenda n 7 do senador eduardo gomes ação"
        },
        {
            "data": "04/11/2024",
            "órgão": "plen  plenário do senado federal",
            "situação": null,
            "ação": "recebido o requerimento n 743 de 2024 de líderes solicitando urgência para a matéria ação publicado no dsf páginas 7071  dsf n 190"
        },
        {
            "data": "04/11/2024",
            "órgão": "plen  plenário do senado federal",
            "situação": null,
            "ação": "recebida a emenda n 6 do senador sérgio petecão ação"
        },
        {
            "data": "04/11/2024",
            "órgão": "plen  plenário do senado federal",
            "situação": null,
            "ação": "recebidas as emendas ns 4 e 5 do senador alan rick ação"
        },
        {
            "data": "04/11/2024",
            "órgão": "plen  plenário do senado federal",
            "situação": null,
            "ação": "recebida a emenda n 3 da senadora soraya thronicke ação"
        },
        {
            "data": "04/11/2024",
            "órgão": "plen  plenário do senado federal",
            "situação": null,
            "ação": "recebido o relatório da senadora leila barros ação"
        },
        {
            "data": "04/11/2024",
            "órgão": "plen  plenário do senado federal",
            "situação": null,
            "ação": "recebida a emenda n 2 do senador laércio oliveira ação"
        },
        {
            "data": "04/11/2024",
            "órgão": "plen  plenário do senado federal",
            "situação": null,
            "ação": "designada relatora de plenário a senadora leila barros pendente de apresentação de requerimento de urgência ação"
        },
        {
            "data": "04/11/2024",
            "órgão": "plen  plenário do senado federal",
            "situação": null,
            "ação": "recebida a emenda n 1 da senadora margareth buzetti ação"
        },
        {
            "data": "02/11/2024",
            "órgão": "plen  plenário do senado federal",
            "situação": "incluída em ordem do dia",
            "ação": "incluído em ordem do dia da sessão deliberativa extraordinária semipresencial de 05/11/2024"
        },
        {
            "data": "07/02/2024",
            "órgão": "plen  plenário do senado federal",
            "situação": "aguardando despacho",
            "ação": "autuado o projeto de lei n 182/2024 proveniente da câmara dos deputados o projeto vai à publicação"
        }
    ],
    "documentos": [
        {
            "documento": "pl 182/2024",
            "data": "07/02/2024",
            "autor": "câmara dos deputados",
            "local": "plenário do senado federal",
            "ação legislativa": "autuado o projeto de lei n 182/2024 proveniente da câmara dos deputados o projeto vai à publicação",
            "descrição/Ementa": null
        },
        {
            "documento": "avulso inicial da matéria",
            "data": "07/02/2024",
            "autor": "senado federal",
            "local": "null",
            "ação legislativa": null,
            "descrição/Ementa": ""
        },
        {
            "documento": "ofício",
            "data": "27/03/2024",
            "autor": "cidadão alexandre victor borges scavardoni",
            "local": "plenário do senado federal",
            "ação legislativa": null,
            "descrição/Ementa": "solicita apoio e  celeridade na tramitação do pl 182/2024 que versa sobre a regulamentação do mercado de mitigação de carbono e emissões de gases poluentes bem como a possibilidade de atribuir a relatoria do referido projeto à senadora tereza cristina encaminha nota técnica a favor do pl"
        },
        {
            "documento": "correspondência eletrônica",
            "data": "24/04/2024",
            "autor": "cidadão alexandre victor borges scavardoni",
            "local": "plenário do senado federal",
            "ação legislativa": null,
            "descrição/Ementa": "solicitação de aprovação urgente do pl 182/2024 com emissão de nota técnica do referido projeto"
        },
        {
            "documento": "ofício",
            "data": "12/08/2024",
            "autor": "indústria brasileira de árvores  ibá",
            "local": "null",
            "ação legislativa": null,
            "descrição/Ementa": "pg 10 atividade legislativa projeto de lei n 182 de 2024 documentos necessidade de correção do texto referente à pl de carbono n 182/2024"
        },
        {
            "documento": "ofício",
            "data": "12/08/2024",
            "autor": "fórum do meio ambiente e sustentabilidade do setor elétrico  fmase",
            "local": "null",
            "ação legislativa": null,
            "descrição/Ementa": "projeto de lei n 182/2024 que institui o sistema brasileiro de comércio de emissões de gases de efeito estufa sbce e altera as leis ns 12187 de 29 de dezembro de 2009 12651 de 25 de maio de 2012 código florestal 6385 de 7 de dezembro de 1976 11033 de 21 de dezembro de 2004 e 6015 de 31 de dezembro de 1973 lei de registros públicos"
        },
        {
            "documento": "ofício",
            "data": "17/09/2024",
            "autor": "fiesp",
            "local": "null",
            "ação legislativa": null,
            "descrição/Ementa": "alerta sobre proposições que podem acarretar significativo aumento de custos para a indústria brasileira"
        },
        {
            "documento": "emenda 1 plen  pl",
            "data": "04/11/2024",
            "autor": "senadora margareth buzetti psd/mt",
            "local": "plenário do senado federal",
            "ação legislativa": "recebida a emenda n 1 da senadora margareth buzetti",
            "descrição/Ementa": "emenda  ao pl 182/2024  crédito de carbono"
        },
        {
            "documento": "emenda 2 plen  pl",
            "data": "04/11/2024",
            "autor": "senador laércio oliveira pp/se",
            "local": "plenário do senado federal",
            "ação legislativa": "recebida a emenda n 2 do senador laércio oliveira",
            "descrição/Ementa": "emenda  ao pl 182/2024"
        },
        {
            "documento": "relatório legislativo",
            "data": "04/11/2024",
            "autor": "senadora leila barros pdt/df",
            "local": "plenário do senado federal",
            "ação legislativa": "recebido o relatório da senadora leila barros",
            "descrição/Ementa": "pela aprovação do pl 182/2024 na forma de substitutivo"
        },
        {
            "documento": "emenda 4 plen  pl",
            "data": "04/11/2024",
            "autor": "senador alan rick união/ac",
            "local": "plenário do senado federal",
            "ação legislativa": "recebidas as emendas ns 4 e 5 do senador alan rick",
            "descrição/Ementa": "emenda  ao pl 182/2024  setores estratégicos"
        },
        {
            "documento": "pg 11 atividade legislativa projeto de lei n 182 de 2024 documentos emenda 3 plen  pl",
            "data": "04/11/2024",
            "autor": "senadora soraya thronicke podemos/ms",
            "local": "plenário do senado federal",
            "ação legislativa": "recebida a emenda n 3 da senadora soraya thronicke",
            "descrição/Ementa": "emenda  ao pl 182/2024 crve"
        },
        {
            "documento": "emenda 5 plen  pl",
            "data": "04/11/2024",
            "autor": "senador alan rick união/ac",
            "local": "plenário do senado federal",
            "ação legislativa": "recebidas as emendas ns 4 e 5 do senador alan rick",
            "descrição/Ementa": "emenda  ao pl 182/2024  ganhos de intensidade"
        },
        {
            "documento": "emenda 6 plen  pl",
            "data": "04/11/2024",
            "autor": "senador sérgio petecão psd/ac",
            "local": "plenário do senado federal",
            "ação legislativa": "recebida a emenda n 6 do senador sérgio petecão",
            "descrição/Ementa": "emenda  ao pl 182/2024  responsável técnico"
        },
        {
            "documento": "rqs 743/2024",
            "data": "04/11/2024",
            "autor": "líder do bloco parlamentar da resistência democrática otto alencar psd/ba líder do bloco parlamentar aliança laércio",
            "local": "plenário do senado federal",
            "ação legislativa": "recebido o requerimento n 743 de 2024 de líderes solicitando urgência para a matéria",
            "descrição/Ementa": "requer urgência para o projeto de lei n 182/2024 nos termos dos arts 336 iii e 338 iii do regimento interno do senado federal"
        },
        {
            "documento": "emenda 8 plen  pl",
            "data": "05/11/2024",
            "autor": "senador eduardo braga mdb/am",
            "local": "plenário do senado federal",
            "ação legislativa": "recebida a emenda n 8 do senador eduardo braga",
            "descrição/Ementa": "emenda  ao pl 182/2024  6 art 43"
        },
        {
            "documento": "emenda 7 plen  pl",
            "data": "05/11/2024",
            "autor": "senador eduardo gomes pl/to",
            "local": "plenário do senado federal",
            "ação legislativa": "recebida a emenda n 7 do senador eduardo gomes",
            "descrição/Ementa": "pg 12 atividade legislativa projeto de lei n 182 de 2024 documentos emenda  ao substitutivo do pl 182/2024"
        },
        {
            "documento": "emenda 13 plen  pl",
            "data": "05/11/2024",
            "autor": "senador zequinha marinho podemos/pa",
            "local": "plenário do senado federal",
            "ação legislativa": "recebidas as emendas ns 13 a 15 do senador zequinha marinho",
            "descrição/Ementa": "emenda  ao pl 182/2024  fpa 3"
        },
        {
            "documento": "emenda 14 plen  pl",
            "data": "05/11/2024",
            "autor": "senador zequinha marinho podemos/pa",
            "local": "plenário do senado federal",
            "ação legislativa": "recebidas as emendas ns 13 a 15 do senador zequinha marinho",
            "descrição/Ementa": "emenda  ao pl 182/2024  4"
        },
        {
            "documento": "emenda 15 plen  pl",
            "data": "05/11/2024",
            "autor": "senador zequinha marinho podemos/pa",
            "local": "plenário do senado federal",
            "ação legislativa": "recebidas as emendas ns 13 a 15 do senador zequinha marinho",
            "descrição/Ementa": "emenda  ao pl 182/2024  fpa"
        },
        {
            "documento": "emenda 9 plen  pl",
            "data": "05/11/2024",
            "autor": "senador mecias de jesus republicanos/rr",
            "local": "plenário do senado federal",
            "ação legislativa": "recebidas as emendas ns 9 e 10 do senador mecias de jesus",
            "descrição/Ementa": "emenda  ao pl 182/2024"
        },
        {
            "documento": "emenda 10 plen  pl",
            "data": "05/11/2024",
            "autor": "senador mecias de jesus republicanos/rr",
            "local": "plenário do senado federal",
            "ação legislativa": "recebidas as emendas ns 9 e 10 do senador mecias de jesus",
            "descrição/Ementa": "emenda  ao pl 182/2024"
        },
        {
            "documento": "rqs 745/2024",
            "data": "05/11/2024",
            "autor": "líder do mdb eduardo braga mdb/am",
            "local": "plenário do senado federal",
            "ação legislativa": "recebido o requerimento n 745 de 2024 da liderança do mdb de destaque para votação em separado da emenda n 8",
            "descrição/Ementa": "pg 13 atividade legislativa projeto de lei n 182 de 2024 documentos requer pela liderança do movimento democrático brasileiro mdb destaque para votação em separado da emenda n 8 ao projeto de lei n 182/2024"
        },
        {
            "documento": "emenda 11 plen  pl",
            "data": "05/11/2024",
            "autor": "senador luis carlos heinze pp/rs",
            "local": "plenário do senado federal",
            "ação legislativa": "recebidas as emendas ns 11 e 12 do senador luis carlos heinze",
            "descrição/Ementa": "emenda  01 pl 182/2024"
        },
        {
            "documento": "emenda 12 plen  pl",
            "data": "05/11/2024",
            "autor": "senador luis carlos heinze pp/rs",
            "local": "plenário do senado federal",
            "ação legislativa": "recebidas as emendas ns 11 e 12 do senador luis carlos heinze",
            "descrição/Ementa": "emenda  02  pl 182/2024"
        },
        {
            "documento": "emenda 16 plen  pl",
            "data": "05/11/2024",
            "autor": "senador castellar neto pp/mg",
            "local": "plenário do senado federal",
            "ação legislativa": "recebida a emenda n 16 do senador castellar neto",
            "descrição/Ementa": "emenda  ao pl 182/2024  aplicação de 1 das reservas técnicas de seguradoras"
        },
        {
            "documento": "emenda 17 plen  pl",
            "data": "05/11/2024",
            "autor": "senador esperidião amin pp/sc",
            "local": "plenário do senado federal",
            "ação legislativa": "recebida a emenda n 17 do senador esperidião amin",
            "descrição/Ementa": "emenda  ao pl 182/2024 multas"
        },
        {
            "documento": "rqs 747/2024",
            "data": "05/11/2024",
            "autor": "líder do pl izalci lucas pl/df",
            "local": "plenário do senado federal",
            "ação legislativa": null,
            "descrição/Ementa": "requer pela liderança do partido liberal pl destaque para votação em separado do art 56 do substitutivo ao projeto de lei n 182/2024"
        },
        {
            "documento": "emenda 20 plen  pl",
            "data": "05/11/2024",
            "autor": "senadora tereza cristina pp/ms",
            "local": "plenário do senado federal",
            "ação legislativa": null,
            "descrição/Ementa": "emenda  ao pl 182/2024"
        },
        {
            "documento": "emenda 21 plen  pl",
            "data": "05/11/2024",
            "autor": "senador mecias de jesus republicanos/rr",
            "local": "plenário do senado federal",
            "ação legislativa": "recebida a emenda n 21 do senador mecias de jesus",
            "descrição/Ementa": "emenda  ao pl 182/2024"
        },
        {
            "documento": "emenda 18 plen  pl",
            "data": "05/11/2024",
            "autor": "senador luis carlos heinze pp/rs",
            "local": "plenário do senado federal",
            "ação legislativa": "recebida a emenda n 18 do senador luis carlos heinze",
            "descrição/Ementa": "emenda  03  pl 182/2024"
        },
        {
            "documento": "emenda 19 plen  pl",
            "data": "05/11/2024",
            "autor": "senador luis carlos heinze pp/rs",
            "local": "plenário do senado federal",
            "ação legislativa": "recebida a emenda n 19 do senador luis carlos heinze",
            "descrição/Ementa": "emenda 04  pl 182/2024"
        },
        {
            "documento": "of 197/2024  gabinete do",
            "data": "05/11/2024",
            "autor": "senador eduardo girão novo/ce",
            "local": "plenário do senado federal",
            "ação legislativa": null,
            "descrição/Ementa": "declaração de voto contrário ao pl 182/2024"
        },
        {
            "documento": "rqs 748/2024",
            "data": "05/11/2024",
            "autor": "líder do pl izalci lucas pl/df",
            "local": "plenário do senado federal",
            "ação legislativa": null,
            "descrição/Ementa": "requer pela liderança do partido liberal pl destaque para votação em separado dos 2 e 3 do art 28 do substitutivo ao projeto de lei n 182/2024"
        },
        {
            "documento": "emenda 22 plen  pl",
            "data": "05/11/2024",
            "autor": "senador esperidião amin pp/sc",
            "local": "plenário do senado federal",
            "ação legislativa": null,
            "descrição/Ementa": "emenda  ao pl 182/2024 carvão"
        },
        {
            "documento": "emenda 23 plen  pl",
            "data": "05/11/2024",
            "autor": "senador rogerio marinho pl/rn",
            "local": "plenário do senado federal",
            "ação legislativa": "recebida a emenda n 23 do senador rogerio marinho",
            "descrição/Ementa": "metodologias internacionais consagradas"
        },
        {
            "documento": "emenda 24 plen  pl",
            "data": "05/11/2024",
            "autor": "senadora professora dorinha seabra união/to",
            "local": "plenário do senado federal",
            "ação legislativa": "recebida a emenda n 24 da senadora professora dorinha seabra",
            "descrição/Ementa": "emenda ao pl 182_2024"
        },
        {
            "documento": "avulso de emendas",
            "data": "05/11/2024",
            "autor": "senado federal",
            "local": "null",
            "ação legislativa": null,
            "descrição/Ementa": ""
        },
        {
            "documento": "ofício",
            "data": "05/11/2024",
            "autor": "ouvidsf  ouvidoria do senado federal",
            "local": "null",
            "ação legislativa": null,
            "descrição/Ementa": "manifestação recebida na ouvidoria do senado  autuação 2814870"
        },
        {
            "documento": "rqs 750/2024",
            "data": "05/11/2024",
            "autor": "senador esperidião amin pp/sc",
            "local": "plenário do senado federal",
            "ação legislativa": "recebido o requerimento n 750 de 2024 do senador esperidião amin solicitando a retirada definitiva da emenda n 22",
            "descrição/Ementa": "requer a retirada definitiva da emenda n 22 ao projeto de lei n 182/2024"
        },
        {
            "documento": "emenda 25 plen  pl",
            "data": "05/11/2024",
            "autor": "senador esperidião amin pp/sc",
            "local": "plenário do senado federal",
            "ação legislativa": "recebida a emenda n 25 do senador esperidião amin",
            "descrição/Ementa": "emenda  ao pl 182/2024 carbono sustentável  ajustada"
        },
        {
            "documento": "pg 16 atividade legislativa projeto de lei n 182 de 2024 documentos emenda 26 plen  pl",
            "data": "11/11/2024",
            "autor": "senador veneziano vital do rêgo mdb/pb",
            "local": "plenário do senado federal",
            "ação legislativa": "recebida a emenda n 26 do senador veneziano vital do rêgo",
            "descrição/Ementa": "emenda  pl 182/2024 mecanismos de precificação"
        },
        {
            "documento": "emenda 27 plen  pl",
            "data": "11/11/2024",
            "autor": "senador efraim filho união/pb",
            "local": "plenário do senado federal",
            "ação legislativa": "recebida a emenda n 27 do senador efraim filho",
            "descrição/Ementa": "emenda ao substitutivo do pl 182/2024  conceito de crédito de carbono"
        },
        {
            "documento": "emenda 28 plen  pl",
            "data": "11/11/2024",
            "autor": "senador esperidião amin pp/sc",
            "local": "plenário do senado federal",
            "ação legislativa": "recebida a emenda n 28 do senador esperidião amin",
            "descrição/Ementa": "emenda  ao pl 182/2024 transferência de crédito internacional"
        },
        {
            "documento": "emenda 30 plen  pl",
            "data": "11/11/2024",
            "autor": "senador zequinha marinho podemos/pa",
            "local": "plenário do senado federal",
            "ação legislativa": "recebidas as emendas ns 30 a 32 do senador zequinha marinho",
            "descrição/Ementa": "emenda  ao pl 182/2024"
        },
        {
            "documento": "emenda 31 plen  pl",
            "data": "11/11/2024",
            "autor": "senador zequinha marinho podemos/pa",
            "local": "plenário do senado federal",
            "ação legislativa": "recebidas as emendas ns 30 a 32 do senador zequinha marinho",
            "descrição/Ementa": "emenda  ao pl 182/2024"
        },
        {
            "documento": "emenda 32 plen  pl",
            "data": "11/11/2024",
            "autor": "senador zequinha marinho podemos/pa",
            "local": "plenário do senado federal",
            "ação legislativa": "recebidas as emendas ns 30 a 32 do senador zequinha marinho",
            "descrição/Ementa": "emenda  ao pl 182/2024 "
        },
        {
            "documento": "pg 17 atividade legislativa projeto de lei n 182 de 2024 documentos emenda 29 plen  pl",
            "data": "11/11/2024",
            "autor": "senador jaime bagattoli pl/ro",
            "local": "plenário do senado federal",
            "ação legislativa": "recebida a emenda n 29 do senador jaime bagattoli",
            "descrição/Ementa": "emenda  ao pl 182/2024"
        },
        {
            "documento": "emenda 33 plen  pl",
            "data": "11/11/2024",
            "autor": "senadora soraya thronicke podemos/ms",
            "local": "plenário do senado federal",
            "ação legislativa": "recebidas as emendas ns 33 e 34 da senadora soraya thronicke",
            "descrição/Ementa": "emenda 2 ao pl 182/2024 abbi"
        },
        {
            "documento": "emenda 34 plen  pl",
            "data": "11/11/2024",
            "autor": "senadora soraya thronicke podemos/ms",
            "local": "plenário do senado federal",
            "ação legislativa": "recebidas as emendas ns 33 e 34 da senadora soraya thronicke",
            "descrição/Ementa": "emenda  ao pl 182/2024 supressão 3 e 4 do art 28"
        },
        {
            "documento": "emenda 35 plen  pl",
            "data": "11/11/2024",
            "autor": "senador laércio oliveira pp/se",
            "local": "plenário do senado federal",
            "ação legislativa": "recebida a emenda n 35 do senador laércio oliveira",
            "descrição/Ementa": "em  emenda  ao pl 182/2024_art 30 3"
        },
        {
            "documento": "relatório legislativo",
            "data": "11/11/2024",
            "autor": "senadora leila barros pdt/df",
            "local": "plenário do senado federal",
            "ação legislativa": "recebido novo relatório da senadora leila barros",
            "descrição/Ementa": "pela aprovação do pl 182 de 2024 ne forma de substitutivo"
        },
        {
            "documento": "emenda 36 plen  pl",
            "data": "12/11/2024",
            "autor": "senador efraim filho união/pb",
            "local": "plenário do senado federal",
            "ação legislativa": "recebida a emenda n 36 do senador efraim filho",
            "descrição/Ementa": "emenda  ao pl 182/2024  art 43  5  obrigatoriedade da escrituração do contrato"
        },
        {
            "documento": "pg 18 atividade legislativa projeto de lei n 182 de 2024 documentos emenda 37 plen  pl",
            "data": "12/11/2024",
            "autor": "senador zequinha marinho podemos/pa",
            "local": "plenário do senado federal",
            "ação legislativa": "recebida a emenda n 37 do senador zequinha marinho",
            "descrição/Ementa": "emenda  ao pl 182/2024"
        },
        {
            "documento": "emenda 38 plen  pl",
            "data": "12/11/2024",
            "autor": "senador nelsinho trad psd/ms",
            "local": "plenário do senado federal",
            "ação legislativa": "recebidas as emendas n  38 e 39 do senador nelsinho trad",
            "descrição/Ementa": "emenda  ao pl 182/2024  credito de carbono"
        },
        {
            "documento": "emenda 39 plen  pl",
            "data": "12/11/2024",
            "autor": "senador nelsinho trad psd/ms",
            "local": "plenário do senado federal",
            "ação legislativa": "recebidas as emendas n  38 e 39 do senador nelsinho trad",
            "descrição/Ementa": "emenda  ao pl 182/2024  credito de carbono"
        },
        {
            "documento": "emenda 40 plen  pl",
            "data": "12/11/2024",
            "autor": "senador jayme campos união/mt",
            "local": "plenário do senado federal",
            "ação legislativa": "recebida a emenda n 40 do senador jayme campos",
            "descrição/Ementa": "emenda  ao pl 182/2024"
        },
        {
            "documento": "emenda 41 plen  pl",
            "data": "12/11/2024",
            "autor": "senador alan rick união/ac",
            "local": "plenário do senado federal",
            "ação legislativa": "recebida a emenda n 41 do senador alan rick",
            "descrição/Ementa": "emenda  ao pl 182/2024  tratamento de resíduos"
        },
        {
            "documento": "emenda 42 plen  pl",
            "data": "12/11/2024",
            "autor": "senador rogerio marinho pl/rn",
            "local": "plenário do senado federal",
            "ação legislativa": "recebida a emenda n 42 do senador rogério marinho",
            "descrição/Ementa": "emenda  ao pl 182/2024  oitiva dos setores regulados"
        },
        {
            "documento": "pg 19 atividade legislativa projeto de lei n 182 de 2024 documentos emenda 43 plen  pl",
            "data": "12/11/2024",
            "autor": "senador marcos rogério pl/ro",
            "local": "plenário do senado federal",
            "ação legislativa": "recebida a emenda n 43 do senador marcos rogério",
            "descrição/Ementa": "emenda ao substitutivo apresentado ao pl n 182/2024 recebimento de receitas sobre vegetação existente"
        },
        {
            "documento": "emenda 44 plen  pl",
            "data": "12/11/2024",
            "autor": "senador carlos portinho pl/rj",
            "local": "plenário do senado federal",
            "ação legislativa": "recebidas as emendas ns 44 45 e 46 do senador carlos portinho",
            "descrição/Ementa": "emenda  ao pl 182/2024 art 1 incluir  6"
        },
        {
            "documento": "emenda 45 plen  pl",
            "data": "12/11/2024",
            "autor": "senador carlos portinho pl/rj",
            "local": "plenário do senado federal",
            "ação legislativa": "recebidas as emendas ns 44 45 e 46 do senador carlos portinho",
            "descrição/Ementa": "emenda parag 1 do art 21   ao pl 182/2024"
        },
        {
            "documento": "emenda 46 plen  pl",
            "data": "12/11/2024",
            "autor": "senador carlos portinho pl/rj",
            "local": "plenário do senado federal",
            "ação legislativa": "recebidas as emendas ns 44 45 e 46 do senador carlos portinho",
            "descrição/Ementa": "emenda  ao 2 do pl 182/2024"
        },
        {
            "documento": "emenda 50 plen  pl",
            "data": "12/11/2024",
            "autor": "senadora soraya thronicke podemos/ms",
            "local": "plenário do senado federal",
            "ação legislativa": "recebida a emenda n 50 da senadora soraya thronicke",
            "descrição/Ementa": "emenda art 56 do pl 182/2024"
        },
        {
            "documento": "emenda 47 plen  pl",
            "data": "12/11/2024",
            "autor": "senador mecias de jesus republicanos/rr",
            "local": "plenário do senado federal",
            "ação legislativa": "recebidas as emendas ns 47e 48 do senador mecias de jesus",
            "descrição/Ementa": "emenda limites ao pl 182/2024"
        },
        {
            "documento": "pg 20 atividade legislativa projeto de lei n 182 de 2024 documentos emenda 48 plen  pl",
            "data": "12/11/2024",
            "autor": "senador mecias de jesus republicanos/rr",
            "local": "plenário do senado federal",
            "ação legislativa": "recebidas as emendas ns 47e 48 do senador mecias de jesus",
            "descrição/Ementa": "emenda limites v3 ao pl 182/2024"
        },
        {
            "documento": "emenda 49 plen  pl",
            "data": "12/11/2024",
            "autor": "senador dr hiran pp/rr",
            "local": "plenário do senado federal",
            "ação legislativa": "recebida a emenda n 49 do senador dr hiran",
            "descrição/Ementa": "emenda  ao pl 182/2024  isonomia para tratamento de carbono produtos nacionais e importados"
        },
        {
            "documento": "rqs 765/2024",
            "data": "12/11/2024",
            "autor": "líder do pl carlos portinho pl/rj",
            "local": "plenário do senado federal",
            "ação legislativa": null,
            "descrição/Ementa": "requer pela liderança do pl destaque para votação em separado do emenda n 42 ao projeto de lei n 182/2024"
        },
        {
            "documento": "rqs 766/2024",
            "data": "12/11/2024",
            "autor": "líder do pl carlos portinho pl/rj",
            "local": "plenário do senado federal",
            "ação legislativa": null,
            "descrição/Ementa": "requer a retirada definitiva dos requerimentos ns 747 e 748 de 2024"
        },
        {
            "documento": "rqs 767/2024",
            "data": "12/11/2024",
            "autor": "líder do pl carlos portinho pl/rj",
            "local": "plenário do senado federal",
            "ação legislativa": null,
            "descrição/Ementa": "requer pela liderança do partido liberal destaque para votação em separado da emenda n 43 ao projeto de lei n 182/2024"
        },
        {
            "documento": "emenda 51 plen  pl",
            "data": "12/11/2024",
            "autor": "pg",
            "local": "plenário do senado federal",
            "ação legislativa": "recebida a emenda n 51 do senador carlos portinho",
            "descrição/Ementa": "emenda supressiva questão dos seguros ao pl 182/2024"
        },
        {
            "documento": "rqs 768/2024",
            "data": "12/11/2024",
            "autor": "líder do podemos rodrigo cunha podemos/al",
            "local": "plenário do senado federal",
            "ação legislativa": "recebido o requerimento n 768 de 2024 da liderança do podemos de destaque para votação em separado da emenda n 50",
            "descrição/Ementa": "requer pela liderança do podemos destaque para votação em separado da emenda n 50 ao projeto de lei n 182/2024"
        },
        {
            "documento": "rqs 769/2024",
            "data": "12/11/2024",
            "autor": "líder do pl carlos portinho pl/rj líder do bloco parlamentar independência styvenson valentim podemos/rn líder do",
            "local": "plenário do senado federal",
            "ação legislativa": "recebido o requerimento n 769 de 2024 de líderes solicitando a extinção da urgência para a matéria",
            "descrição/Ementa": "requer a extinção de urgência para o projeto de lei n 182/2024 nos termos do art 352 ii e parágrafo único ii do regimento interno do senado federal"
        },
        {
            "documento": "rqs 770/2024",
            "data": "12/11/2024",
            "autor": "senador laércio oliveira pp/se",
            "local": "plenário do senado federal",
            "ação legislativa": "recebido o requerimento n 770 de 2024 da liderança do pp de destaque para votação em separado da emenda n 25",
            "descrição/Ementa": "requer pela liderança do pp destaque para votação em separado da emenda n 25 ao projeto de lei n 182/2024"
        },
        {
            "documento": "relatório legislativo",
            "data": "12/11/2024",
            "autor": "senadora leila barros pdt/df",
            "local": "plenário do senado federal",
            "ação legislativa": "recebido o relatório da senadora leila barros",
            "descrição/Ementa": "parecer favorável ao pl 182/24 na forma de substitutivo"
        },
        {
            "documento": "rqs 772/2024",
            "data": "12/11/2024",
            "autor": "líder do bloco parlamentar aliança laércio oliveira pp/se",
            "local": "plenário do senado federal",
            "ação legislativa": "recebido o requerimento n 772 de 2024 da liderança do pp de destaque para votação em separado da emenda n 25",
            "descrição/Ementa": "requer pela liderança do pp destaque para votação em separado da emenda n 25 ao projeto de lei n 182/2024"
        },
        {
            "documento": "avulso de emendas pg 22 atividade legislativa projeto de lei n 182 de 2024 documentos",
            "data": "12/11/2024",
            "autor": "senado federal",
            "local": "plenário do senado federal",
            "ação legislativa": null,
            "descrição/Ementa": ""
        },
        {
            "documento": "emenda 52 plen  pl",
            "data": "13/11/2024",
            "autor": "senador efraim filho união/pb",
            "local": "plenário do senado federal",
            "ação legislativa": "recebida a emenda n 52 do senador efraim filho",
            "descrição/Ementa": "emenda ao art 26 do substitutivo"
        },
        {
            "documento": "emenda 53 plen  pl",
            "data": "13/11/2024",
            "autor": "senador izalci lucas pl/df",
            "local": "plenário do senado federal",
            "ação legislativa": "recebida a emenda n 53 do senador izalci lucas",
            "descrição/Ementa": "emenda 1 ao pl 182/2024"
        },
        {
            "documento": "emenda 54 plen  pl",
            "data": "13/11/2024",
            "autor": "senador alan rick união/ac",
            "local": "plenário do senado federal",
            "ação legislativa": "recebida a emenda n 54 do senador alan rick",
            "descrição/Ementa": "emenda  ao pl 182/2024"
        },
        {
            "documento": "emenda 55 plen  pl",
            "data": "13/11/2024",
            "autor": "senador carlos portinho pl/rj",
            "local": "plenário do senado federal",
            "ação legislativa": "recebida a emenda n 55 do senador carlos portinho",
            "descrição/Ementa": "emenda ao art 56 do subs ao pl 182/2024  autorizativa investimento seguro"
        },
        {
            "documento": "emenda 56 plen  pl",
            "data": "13/11/2024",
            "autor": "senador luis carlos heinze pp/rs",
            "local": "plenário do senado federal",
            "ação legislativa": "recebida a emenda n 56 do luis carlos heinze",
            "descrição/Ementa": "emenda  ao pl 182/2024 resíduos"
        },
        {
            "documento": "emenda 57 plen  pl",
            "data": "13/11/2024",
            "autor": "pg",
            "local": "plenário do senado federal",
            "ação legislativa": "recebida a emenda n 57 do marcos rogério",
            "descrição/Ementa": "emenda  ao pl 182/2024 art 43 acrescentando o 17"
        },
        {
            "documento": "relatório legislativo",
            "data": "13/11/2024",
            "autor": "senadora leila barros pdt/df",
            "local": "plenário do senado federal",
            "ação legislativa": "recebido o relatório da senadora leila barros",
            "descrição/Ementa": "pela aprovação do pl 182/2024"
        },
        {
            "documento": "rqs 779/2024",
            "data": "13/11/2024",
            "autor": "líder do republicanos mecias de jesus republicanos/rr",
            "local": "plenário do senado federal",
            "ação legislativa": null,
            "descrição/Ementa": "requer pela liderança do republicanos destaque para votação em separado da emenda n 26 ao pl 182/2024"
        },
        {
            "documento": "rqs 780/2024",
            "data": "13/11/2024",
            "autor": "líder do pl carlos portinho pl/rj",
            "local": "plenário do senado federal",
            "ação legislativa": null,
            "descrição/Ementa": "requer a retirada definitiva do requerimento n 767 de 2024"
        },
        {
            "documento": "rqs 781/2024",
            "data": "13/11/2024",
            "autor": "líder do pl carlos portinho pl/rj",
            "local": "plenário do senado federal",
            "ação legislativa": null,
            "descrição/Ementa": "requer pela liderança do pl destaque para votação em separado da emenda n 57 ao projeto de lei n 182/2024"
        },
        {
            "documento": "emenda 58 plen  pl",
            "data": "13/11/2024",
            "autor": "senador alan rick união/ac",
            "local": "plenário do senado federal",
            "ação legislativa": "recebida a emenda n 58 do senador alan rick",
            "descrição/Ementa": "emenda  ao pl 182/2024"
        },
        {
            "documento": "pg 24 atividade legislativa projeto de lei n 182 de 2024 documentos rqs 782/2024",
            "data": "13/11/2024",
            "autor": "líder do união efraim filho união/pb",
            "local": "plenário do senado federal",
            "ação legislativa": "recebido o requerimento n 782 de 2024 da liderança do união de destaque para votação em separado da emenda n 58",
            "descrição/Ementa": "requer pela liderança do união destaque para votação em separado da emenda n 58 ao projeto de lei n 182/2024"
        },
        {
            "documento": "listagem ou relatório",
            "data": "13/11/2024",
            "autor": "senado federal",
            "local": "plenário do senado federal",
            "ação legislativa": null,
            "descrição/Ementa": "votação nominal da emenda n 58 ao substitutivo da relatora ao projeto de lei n 182 de 2024 destacada"
        },
        {
            "documento": "emenda 59 plen  pl",
            "data": "13/11/2024",
            "autor": "senadora leila barros pdt/df",
            "local": "plenário do senado federal",
            "ação legislativa": null,
            "descrição/Ementa": "emenda n 59 substitutivo da relatora  parecer n 186 de 2024plen/sf"
        },
        {
            "documento": "ps 186/2024  plen",
            "data": "13/11/2024",
            "autor": "senadora leila barros pdt/df",
            "local": "plenário do senado federal",
            "ação legislativa": null,
            "descrição/Ementa": "parecer n 186 de 2024plen/sf com complemento por notas taquigráficas"
        },
        {
            "documento": "ps 187/2024  plen",
            "data": "13/11/2024",
            "autor": "comissão diretora do senado federal",
            "local": "plenário do senado federal",
            "ação legislativa": null,
            "descrição/Ementa": "pg 25 atividade legislativa projeto de lei n 182 de 2024 documentos 69 encaminhado à publicação o parecer n 187 de 2024plen/sf da comissão diretora oferecendo a redação para o turno suplementar encerrada a discussão em turno suplementar sem emendas o substitutivo é dado como definitivamente adotado sem votação a matéria retorna à câmara dos deputados parecer n 187/2024cdir"
        },
        {
            "documento": "avulso de emendas",
            "data": "13/11/2024",
            "autor": "senado federal",
            "local": "plenário do senado federal",
            "ação legislativa": null,
            "descrição/Ementa": ""
        },
        {
            "documento": "ofsf 1291/2024",
            "data": "19/11/2024",
            "autor": "primeirosecretário do senado federal",
            "local": "comissão diretora do senado federal",
            "ação legislativa": null,
            "descrição/Ementa": "encaminha à revisão da câmara dos deputados o substitutivo do projeto de lei n 182 de 2024"
        },
        {
            "documento": "minuta",
            "data": "19/11/2024",
            "autor": "senado federal",
            "local": "secretaria de expediente",
            "ação legislativa": "anexado o texto revisado",
            "descrição/Ementa": "autógrafo  pl 182/2024"
        },
        {
            "documento": "autógrafo  pl 182/2024",
            "data": "19/11/2024",
            "autor": "senado federal",
            "local": "secretaria de expediente",
            "ação legislativa": null,
            "descrição/Ementa": "institui o sistema brasileiro de comércio de emissões de gases de efeito estufa sbce e altera as leis ns 12187 de 29 de dezembro de 2009 12651 de 25 de maio de 2012 código florestal 6385 de 7 de dezembro de 1976 11033 de 21 de dezembro de 2004 e 6015 de 31 de dezembro de 1973 lei de registros públicos"
        },
        {
            "documento": "of 603/2024  câmara dos",
            "data": "26/11/2024",
            "autor": "primeirosecretário da câmara dos deputados",
            "local": "plenário do senado federal",
            "ação legislativa": null,
            "descrição/Ementa": "comunica o envio à sanção do projeto de lei n 182 de 2024"
        },
        {
            "documento": "quadro comparativo",
            "data": "26/11/2024",
            "autor": "congresso nacional",
            "local": "pg",
            "ação legislativa": null,
            "descrição/Ementa": "comparação entre a legislação vigente o texto aprovado na câmara dos deputados e o substitutivo aprovado pelo senado federal"
        }
    ]
}