{
    "atividade legislativa": "Projeto de Lei n° 1039, de 2020",
    "iniciativa": "Senador Esperidião Amin (PP/SC)",
    "ementa": "Concede ao Município de Irineópolis, no Estado de Santa Catarina, o título de Capital Nacional do Trator.",
    "explicação da ementa": "Declara o Município de Irineópolis-SC como capital nacional do trator.",
    "assunto": "Honorífico  - Homenagem",
    "despacho": "04/03/2022\nDecisão da Presidência\nAnálise - Tramitação sucessiva, Instrução da matéria\n(SF-CE) Comissão de Educação e Cultura",
    "relatoria": "CE - (Comissão de Educação e Cultura)\nRelator(es):\nSenador Dário Berger (encerrado em 10/01/2023 - Fim de\nLegislatura)\nSenadora Ivete da Silveira (encerrado em 25/04/2023 -\nSubstituído por \"ad hoc\")\nSenadora Damares Alves (Relator Ad hoc) (encerrado em\n25/04/2023 - Deliberação da matéria)",
    "tramitação encerrada": {
        "decisão": "Aprovada por Comissão em decisão",
        "destino": "À Câmara dos Deputados",
        "último local": "12/11/2024 - Secretaria de Expediente",
        "último estado": "13/11/2024 - TRANSFORMADA EM\nNORMA JURÍDICA"
    },
    "tramitação": [
        {
            "data": "13/11/2024",
            "órgão": "SF-SEXPE - Secretaria de Expediente",
            "situação": null,
            "ação": "Remetido Ofício SF n.º 1274, de 13/11/24, ao Senhor Ministro de Estado Chefe da Casa Civil da Presidência da República,\nencaminhando a Mensagem SF n.º 233/24, ao Excelentíssimo Senhor Presidente da República, participando a promulgação da\nLei nº 15.015, de 12 de novembro de 2024, nos termos do § 7º do art. 66 da Constituição Federal.\nRemetido Ofício SF n.º 1275, de 13/11/24, ao Senhor Primeiro-Secretário da Câmara dos Deputados, comunicando que foi\npromulgada pelo Senhor Presidente do Senado Federal, nos termos do § 7º do art. 66 da Constituição Federal, a Lei nº 15.015,\nde 12 de novembro de 2024.\nAção:"
        },
        {
            "data": "13/11/2024",
            "órgão": "SF-SEXPE - Secretaria de Expediente",
            "situação": null,
            "ação": "(CN) MESA.\nPROMULGADA. LEI N° 15015 DE 2024.\nDOU (Diário Oficial da União) - 13/11/2024 - Seção I - pág. 9.\nPromulgada em 12/11/2024.\nAção:"
        },
        {
            "data": "11/11/2024",
            "órgão": "PLEN - Plenário do Senado Federal",
            "situação": null,
            "ação": "Encaminhado à publicação o Ofício nº 1.556, de 2024, na origem, do Ministro de Estado Chefe da Casa Civil da Presidência da\nAção:\npg\n1\nAtividade Legislativa\nProjeto de Lei n° 1039, de 2020\nTRAMITAÇÃO\nRepública, que restitui o autógrafo do presente projeto, não sancionado expressamente.\nA matéria vai à promulgação, nos termos do § 7º do art. 66 da Constituição Federal.\nPublicado no DSF Páginas 74-75 - DSF nº 193"
        },
        {
            "data": "17/10/2024",
            "órgão": "PLEN - Plenário do Senado Federal",
            "situação": null,
            "ação": "Encaminhado à publicação o Ofício da Câmara dos Deputados n° 365, de 2024, na origem, que comunica o envio à sanção do\nProjeto de Lei nº 1.039, de 2020.\nA matéria vai à Secretaria de Expediente.\nAção:\nPublicado no DSF Páginas 82 - DSF nº 179\nPublicado no DSF Páginas 84 - DSF nº 179"
        },
        {
            "data": "18/05/2023",
            "órgão": "SF-SEXPE - Secretaria de Expediente",
            "situação": "REMETIDA À CÂMARA DOS DEPUTADOS",
            "ação": "Remetido Ofício SF nº 320, de 17/05/23, ao Senhor Primeiro-Secretário da Câmara dos Deputados, encaminhando autógrafos do\nprojeto para revisão, nos termos do art. 65 da Constituição Federal."
        },
        {
            "data": "12/05/2023",
            "órgão": "SF-SEXPE - Secretaria de Expediente",
            "situação": null,
            "ação": "Anexado o texto revisado.\nAção:"
        },
        {
            "data": "12/05/2023",
            "órgão": "PLEN - Plenário do Senado Federal",
            "situação": "APROVADA",
            "ação": "Encerrou-se em 11 de maio o prazo para interposição de recurso para apreciação do Projeto pelo Plenário.\nNão foi apresentado recurso.\nA matéria, aprovada terminativamente pela CE, vai à Câmara dos Deputados."
        },
        {
            "data": "12/05/2023",
            "órgão": "PLEN - Plenário do Senado Federal",
            "situação": null,
            "ação": "Anexado o texto final revisado.\nAção:"
        },
        {
            "data": "03/05/2023",
            "órgão": "PLEN - Plenário do Senado Federal",
            "situação": null,
            "ação": "Prazo: Interposição de Recurso a decisão terminativa de Comissão (Art. 91, §§ 3º ao 5º, do RISF). De 05/05/2023 a 11/05/2023.\nPerante a Mesa.\nAção:"
        },
        {
            "data": "03/05/2023",
            "órgão": "PLEN - Plenário do Senado Federal",
            "situação": "AGUARDANDO INTERPOSIÇÃO DE RECURSO",
            "ação": "Encaminhado á publicação o  Ofício nº 66, de 2023, da CE, comunicando a apreciação da matéria, em caráter terminativo.\nConcluída a instrução da matéria, fica aberto o prazo de cinco dias úteis para interposição de recurso, por um décimo dos\nmembros da Casa, para que a matéria seja apreciada pelo Plenário, nos termos do art. 91, §§ 3º a 5º, do Regimento Interno."
        },
        {
            "data": "25/04/2023",
            "órgão": "CE - Comissão de Educação e Cultura",
            "situação": "APRECIADA EM DECISÃO TERMINATIVA PELAS COMISSÕES",
            "ação": "Em reunião realizada em 25/4/2023, foi aprovado terminativamente o projeto (Quórum: 14; Sim: 13; Não: 0; Abstenções: 0)."
        },
        {
            "data": "24/04/2023",
            "órgão": "CE - Comissão de Educação e Cultura",
            "situação": "INCLUÍDA NA PAUTA DA REUNIÃO",
            "ação": "Matéria constante da Pauta da 12ª Reunião da Comissão de Educação, Cultura e Esporte, agendada para o dia 25/04/2023."
        },
        {
            "data": "03/04/2023",
            "órgão": "CE - Comissão de Educação e Cultura",
            "situação": "PRONTA PARA A PAUTA NA COMISSÃO",
            "ação": "Recebido relatório da Senadora Ivete da Silveira, pela aprovação do projeto."
        },
        {
            "data": "22/03/2023",
            "órgão": "CE - Comissão de Educação e Cultura",
            "situação": "MATÉRIA COM A RELATORIA",
            "ação": "Distribuído à Senadora Ivete da Silveira, para emitir relatório."
        },
        {
            "data": "02/02/2023",
            "órgão": "CE - Comissão de Educação e Cultura",
            "situação": "AGUARDANDO DESIGNAÇÃO DO RELATOR",
            "ação": "Matéria aguardando distribuição"
        },
        {
            "data": "21/12/2022",
            "órgão": "CE - Comissão de Educação e Cultura",
            "situação": null,
            "ação": "A proposição continua a tramitar, nos termos do art. 332 do Regimento Interno.\nAção:"
        },
        {
            "data": "20/12/2022",
            "órgão": "CE - Comissão de Educação e Cultura",
            "situação": "PRONTA PARA A PAUTA NA COMISSÃO",
            "ação": "Em reunião realizada em 20/12/2022, a apreciação da matéria foi adiada."
        },
        {
            "data": "12/12/2022",
            "órgão": "CE - Comissão de Educação e Cultura",
            "situação": "INCLUÍDA NA PAUTA DA REUNIÃO",
            "ação": "Matéria constante da Pauta da 32ª Reunião da Comissão de Educação, Cultura e Esporte, agendada para o dia 15/12/2022."
        },
        {
            "data": "13/07/2022",
            "órgão": "CE - Comissão de Educação e Cultura",
            "situação": "PRONTA PARA A PAUTA NA COMISSÃO",
            "ação": "Recebido relatório do Senador Dário Berger com voto pela aprovação do projeto."
        },
        {
            "data": "31/03/2022",
            "órgão": "CE - Comissão de Educação e Cultura",
            "situação": "MATÉRIA COM A RELATORIA",
            "ação": "Distribuído ao Senador Dário Berger, para emitir relatório."
        },
        {
            "data": "15/03/2022",
            "órgão": "CE - Comissão de Educação e Cultura",
            "situação": "AGUARDANDO DESIGNAÇÃO DO RELATOR",
            "ação": "Não foram oferecidas emendas no prazo regimental.\nMatéria aguardando distribuição."
        },
        {
            "data": "04/03/2022",
            "órgão": "CE - Comissão de Educação e Cultura",
            "situação": null,
            "ação": "Prazo: Apresentação de Emendas a projeto terminativo em Comissão (Art. 122, II, \"c\", do RISF). De 08/03/2022 a 14/03/2022.\nPerante a CE.\nAção:"
        },
        {
            "data": "04/03/2022",
            "órgão": "PLEN - Plenário do Senado Federal",
            "situação": "AGUARDANDO RECEBIMENTO DE EMENDAS",
            "ação": "A matéria vai à CE, em decisão terminativa, cabendo apresentação de emendas perante a Comissão pelo prazo de cinco dias\núteis, nos termos do art. 122, II, “c”, do Regimento Interno."
        },
        {
            "data": "27/03/2020",
            "órgão": "PLEN - Plenário do Senado Federal",
            "situação": null,
            "ação": "Encaminhado à publicação no DSF de 02/04/2020.\nAção:\nPublicado no DSF Páginas 775-778 - DSF nº 28"
        },
        {
            "data": "27/03/2020",
            "órgão": "PLEN - Plenário do Senado Federal",
            "situação": null,
            "ação": "Leitura da matéria na sessão do SF nº1, em 27/03/2020.\nAção:"
        }
    ],
    "documentos": [
        {
            "documento": "PL 1039/2020",
            "data": "12/03/2020",
            "autor": "Senador Esperidião Amin (PP/SC)",
            "local": "Plenário do Senado Federal",
            "ação legislativa": null,
            "descrição/Ementa": null
        },
        {
            "documento": "Avulso inicial da matéria",
            "data": "27/03/2020",
            "autor": "Senado Federal",
            "local": "Plenário do Senado Federal",
            "ação legislativa": null,
            "descrição/Ementa": "-"
        },
        {
            "documento": "Relatório Legislativo",
            "data": "13/07/2022",
            "autor": "Senador Dário Berger (PSB/SC)",
            "local": "Comissão de Educação e Cultura",
            "ação legislativa": "Recebido relatório do Senador Dário Berger com voto pela aprovação do projeto.",
            "descrição/Ementa": "RELATÓRIO DO SENADOR DÁRIO BERGER"
        },
        {
            "documento": "Relatório Legislativo",
            "data": "03/04/2023",
            "autor": "Senadora Ivete da Silveira (MDB/SC)",
            "local": "Comissão de Educação e Cultura",
            "ação legislativa": "Recebido relatório da Senadora Ivete da Silveira, pela aprovação do projeto.",
            "descrição/Ementa": "concede ao Município de Irineópolis, no Estado de Santa Catarina, o título de Capital Nacional do Trator"
        },
        {
            "documento": "Listagem ou relatório",
            "data": "25/04/2023",
            "autor": "Comissão de Educação e Cultura",
            "local": "Comissão de Educação e Cultura",
            "ação legislativa": null,
            "descrição/Ementa": "Listagem ou relatório descritivo-Lista de Presença da reunião da 12ª Reunião CE"
        },
        {
            "documento": "Listagem ou relatório",
            "data": "25/04/2023",
            "autor": "Comissão de Educação e Cultura",
            "local": "Comissão de Educação e Cultura",
            "ação legislativa": null,
            "descrição/Ementa": "Listagem ou relatório descritivo-Lista de Votação Nominal da reunião da 12ª Reunião CE"
        },
        {
            "documento": "P.S 30/2023 - CE",
            "data": "25/04/2023",
            "autor": "Comissão de Educação e Cultura",
            "local": "Comissão de Educação e Cultura",
            "ação legislativa": "Em reunião realizada em 25/4/2023, foi aprovado terminativamente o projeto (Quórum: 14; Sim: 13; Não: 0; Abstenções: 0).",
            "descrição/Ementa": "concede ao Município de Irineópolis, no Estado de Santa Catarina, o título de Capital Nacional do Trator"
        },
        {
            "documento": "Ofício",
            "data": "03/05/2023",
            "autor": "Presidente de Comissão",
            "local": "Comissão de Educação e Cultura",
            "ação legislativa": null,
            "descrição/Ementa": "pg\n5\nAtividade Legislativa\nProjeto de Lei n° 1039, de 2020\nDOCUMENTOS\nOfício nº 66/2023/CE"
        },
        {
            "documento": "Texto final revisado - Projeto",
            "data": "12/05/2023",
            "autor": "Núcleo de Redação Legislativa",
            "local": "Plenário do Senado Federal",
            "ação legislativa": "Anexado o texto final revisado.",
            "descrição/Ementa": "Concede ao Município de Irineópolis, no Estado de Santa Catarina, o título de Capital Nacional do Trator."
        },
        {
            "documento": "Minuta",
            "data": "12/05/2023",
            "autor": "Senado Federal",
            "local": "Secretaria de Expediente",
            "ação legislativa": "Anexado o texto revisado.",
            "descrição/Ementa": "OFSF 320/2023"
        },
        {
            "documento": "OFSF 320/2023",
            "data": "18/05/2023",
            "autor": "Primeiro-Secretário do Senado Federal",
            "local": "Comissão Diretora do Senado Federal",
            "ação legislativa": null,
            "descrição/Ementa": "Encaminha à revisão da Câmara dos Deputados o Projeto de Lei n° 1.039 , de 2020."
        },
        {
            "documento": "Autógrafo - PL 1039/2020",
            "data": "18/05/2023",
            "autor": "Senado Federal",
            "local": "Secretaria de Expediente",
            "ação legislativa": null,
            "descrição/Ementa": "Concede ao Município de Irineópolis, no Estado de Santa Catarina, o título de Capital Nacional do Trator."
        },
        {
            "documento": "OFC 365/2024 - Câmara dos",
            "data": "17/10/2024",
            "autor": "Primeiro-Secretário da Câmara dos Deputados",
            "local": "Plenário do Senado Federal",
            "ação legislativa": null,
            "descrição/Ementa": "Comunica o envio à sanção do Projeto de Lei nº 1.039, de 2020."
        },
        {
            "documento": "OF. 1556/2024 - Casa Civil",
            "data": "11/11/2024",
            "autor": "Casa Civil",
            "local": "Plenário do Senado Federal",
            "ação legislativa": null,
            "descrição/Ementa": "Comunica a restituição de autógrafo para promulgação pelo Presidente do Senado Federal (sanção tácita)."
        },
        {
            "documento": "pg\n6\nAtividade Legislativa\nProjeto de Lei n° 1039, de 2020\nDOCUMENTOS\nAutógrafo - PL 1039/2020",
            "data": "12/11/2024",
            "autor": "Senado Federal",
            "local": "null",
            "ação legislativa": null,
            "descrição/Ementa": "Concede ao Município de Irineópolis, no Estado de Santa Catarina, o título de Capital Nacional do Trator."
        },
        {
            "documento": "MPSF 233/2024",
            "data": "13/11/2024",
            "autor": "Presidente do Senado Federal",
            "local": "Comissão Diretora do Senado Federal",
            "ação legislativa": null,
            "descrição/Ementa": "Encaminha à Presidência da República o autógrafo promulgado do Projeto de Lei n° 1.039, de 2020, nos termos dos §§ 3º e 7º do\nart. 66 da Constituição Federal."
        },
        {
            "documento": "OFSF 1274/2024",
            "data": "13/11/2024",
            "autor": "Primeiro-Secretário do Senado Federal",
            "local": "Comissão Diretora do Senado Federal",
            "ação legislativa": null,
            "descrição/Ementa": "Encaminha a Mensagem da Presidência do Senado Federal participando a promulgação do Projeto de Lei n° 1.039, de 2020, nos\ntermos dos §§ 3º e 7º do art. 66 da Constituição Federal."
        },
        {
            "documento": "OFSF 1275/2024",
            "data": "13/11/2024",
            "autor": "Primeiro-Secretário do Senado Federal",
            "local": "Comissão Diretora do Senado Federal",
            "ação legislativa": null,
            "descrição/Ementa": "Encaminha à Câmara dos Deputados cópia de autógrafo promulgado do Projeto de Lei n° 1.039, de 2020, nos termos dos §§ 3º e\n7º do art. 66 da Constituição Federal."
        },
        {
            "documento": "Autógrafo - PL 1039/2020",
            "data": "13/11/2024",
            "autor": "Senado Federal",
            "local": "pg",
            "ação legislativa": null,
            "descrição/Ementa": "Concede ao Município de Irineópolis, no Estado de Santa Catarina, o título de Capital Nacional do Trator."
        }
    ]
}