{
    "atividade legislativa": "projeto de lei n 4448 de 2024",
    "autoria": "câmara dos deputados",
    "ementa": "autoriza o poder executivo federal a conceder subvenção econômica sob a forma de desconto para liquidação ou renegociação de parcelas de operações de crédito rural de custeio de investimento e de industrialização contratadas por mutuários afetados com perdas materiais decorrentes dos eventos climáticos extremos ocorridos nos meses de abril e maio de 2024 nos termos do decreto legislativo n 36 de 7 de maio de 2024 em municípios do estado do rio grande do sul que tiveram estado de calamidade pública ou situação de emergência reconhecidos pelo poder executivo federal autoriza as instituições financeiras a operarem com mutuários nas condições que especifica altera as leis ns 14042 de 19 de agosto de 2020 8427 de 27 de maio de 1992 14981 de 20 de setembro de 2024 e 13001 de 20 de junho de 2014 e revoga as medidas provisórias ns 1247 de 31 de julho de 2024 e 1272 de 25 de outubro de 2024",
    "assunto": "economia e desenvolvimento   finanças públicas",
    "despacho": "27/11/2024 decisão da presidência ao plenário sfplen plenário do senado federal",
    "relatoria": "plen  plenário do senado federal relatores senador paulo paim encerrado em 27/11/2024  matéria deliberada no plenário",
    "tramitação encerrada": {
        "decisão": "aprovada pelo plenário",
        "destino": "à sanção",
        "último local": "03/12/2024  secretaria de expediente",
        "último estado": "02/12/2024  transformada em norma jurídica"
    },
    "tramitação": [
        {
            "data": "04/12/2024",
            "órgão": "sfsexpe  secretaria de expediente",
            "situação": null,
            "ação": "remetido ofício sf n 1333 de 03/12/24 ao senhor primeirosecretário da câmara dos deputados comunicando para os devidos fins que a presidência da república encaminhou ao senado federal a mensagem n 1564 de 2024 na origem restituindo autógrafos do projeto de lei n 4448 de 2024 sancionado e transformado na lei n 15038 de 29 de novembro de 2024 à coarq ação"
        },
        {
            "data": "03/12/2024",
            "órgão": "plen  plenário do senado federal",
            "situação": null,
            "ação": "encaminhada à publicação a mensagem da presidência da república n 1564 de 2024 na origem que restitui autógrafo do ação pg 1 atividade legislativa projeto de lei n 4448 de 2024 tramitação projeto de lei n 4448 de 2024 sancionado e convertido na lei n 15038 de 29 de novembro de 2024 será feita a devida comunicação à câmara dos deputados"
        },
        {
            "data": "02/12/2024",
            "órgão": "sfsexpe  secretaria de expediente",
            "situação": "transformada em norma jurídica",
            "ação": "pr presidência da república sancionada lei 15038 de 2024 dou diário oficial da união  02/12/2024  seção i  págs 1 e 2 sancionada em 29/11/2024"
        },
        {
            "data": "27/11/2024",
            "órgão": "sfsexpe  secretaria de expediente",
            "situação": "remetida à sanção",
            "ação": "remetido ofício sf n 1328 de 27/11/24 ao senhor ministro de estado chefe da casa civil da presidência da república encaminhando a mensagem sf n 243/24 ao excelentíssimo senhor presidente da república submetendo à sanção presidencial autógrafo do projeto remetido ofício sf n 1329 de 27/11/24 ao senhor primeirosecretário da câmara dos deputados comunicando que o projeto foi encaminhado à sanção presidencial"
        },
        {
            "data": "27/11/2024",
            "órgão": "sfsexpe  secretaria de expediente",
            "situação": null,
            "ação": "anexado o texto revisado ação"
        },
        {
            "data": "27/11/2024",
            "órgão": "plen  plenário do senado federal",
            "situação": "aprovada",
            "ação": "168ª sessão deliberativa ordinária  realizada em 27/11/2024 encaminhado à publicação  e aprovado  o requerimento n 829 de 2024 por meio do qual se solicita urgência para a matéria encaminhado à publicação o parecer n 193 de 2024plen/sf proferido pelo senador paulo paim o qual é favorável ao projeto encerrada a discussão da matéria aprovado o projeto o projeto vai à sanção será feita a devida comunicação à câmara dos deputados"
        },
        {
            "data": "27/11/2024",
            "órgão": "plen  plenário do senado federal",
            "situação": null,
            "ação": "recebido o relatório do senador paulo paim ação"
        },
        {
            "data": "27/11/2024",
            "órgão": "plen  plenário do senado federal",
            "situação": null,
            "ação": "designado relator de plenário o senador paulo paim ação"
        },
        {
            "data": "27/11/2024",
            "órgão": "plen  plenário do senado federal",
            "situação": null,
            "ação": "recebido o requerimento n 829 de 2024 de líder solicitando urgência para a matéria ação pg 2 atividade legislativa projeto de lei n 4448 de 2024 tramitação"
        },
        {
            "data": "27/11/2024",
            "órgão": "plen  plenário do senado federal",
            "situação": "aguardando despacho",
            "ação": "autuado o projeto de lei n 4448/2024 proveniente da câmara dos deputados o projeto vai à publicação"
        }
    ],
    "documentos": [
        {
            "documento": "pl 4448/2024",
            "data": "27/11/2024",
            "autor": "câmara dos deputados",
            "local": "plenário do senado federal",
            "ação legislativa": "autuado o projeto de lei n 4448/2024 proveniente da câmara dos deputados o projeto vai à publicação",
            "descrição/Ementa": null
        },
        {
            "documento": "rqs 829/2024",
            "data": "27/11/2024",
            "autor": "líder do bloco parlamentar da resistência democrática eliziane gama psd/ma",
            "local": "plenário do senado federal",
            "ação legislativa": "recebido o requerimento n 829 de 2024 de líder solicitando urgência para a matéria",
            "descrição/Ementa": "requer urgência para o projeto de lei n 4448/2024 nos termos dos arts 336 iii e 338 iii do regimento interno do senado federal"
        },
        {
            "documento": "avulso inicial da matéria",
            "data": "27/11/2024",
            "autor": "senado federal",
            "local": "plenário do senado federal",
            "ação legislativa": "autuado o projeto de lei n 4448/2024 proveniente da câmara dos deputados o projeto vai à publicação",
            "descrição/Ementa": ""
        },
        {
            "documento": "relatório legislativo",
            "data": "27/11/2024",
            "autor": "senador paulo paim pt/rs",
            "local": "plenário do senado federal",
            "ação legislativa": "recebido o relatório do senador paulo paim",
            "descrição/Ementa": "parecer pl 4448 de 2024 crédito rural"
        },
        {
            "documento": "ps 193/2024  plen pg 3 atividade legislativa projeto de lei n 4448 de 2024 documentos",
            "data": "27/11/2024",
            "autor": "senador paulo paim pt/rs",
            "local": "plenário do senado federal",
            "ação legislativa": null,
            "descrição/Ementa": "parecer n 293 de 2024plen/sf"
        },
        {
            "documento": "mpsf 243/2024",
            "data": "27/11/2024",
            "autor": "presidente do senado federal",
            "local": "comissão diretora do senado federal",
            "ação legislativa": null,
            "descrição/Ementa": "encaminha à sanção o projeto de lei n 4448/2024"
        },
        {
            "documento": "ofsf 1329/2024",
            "data": "27/11/2024",
            "autor": "primeirosecretário do senado federal",
            "local": "comissão diretora do senado federal",
            "ação legislativa": null,
            "descrição/Ementa": "comunica à câmara dos deputados o encaminhamento à presidência da república do projeto de lei n 4448/2024"
        },
        {
            "documento": "ofsf 1328/2024",
            "data": "27/11/2024",
            "autor": "primeirosecretário do senado federal",
            "local": "comissão diretora do senado federal",
            "ação legislativa": null,
            "descrição/Ementa": "encaminha a mensagem da presidência do senado federal submetendo à sanção presidencial autógrafos do projeto de lei n 4448/2024"
        },
        {
            "documento": "minuta",
            "data": "27/11/2024",
            "autor": "pg",
            "local": "secretaria de expediente",
            "ação legislativa": "anexado o texto revisado",
            "descrição/Ementa": "autógrafo  pl 4448/2024"
        },
        {
            "documento": "autógrafo  pl 4448/2024",
            "data": "27/11/2024",
            "autor": "senado federal",
            "local": "secretaria de expediente",
            "ação legislativa": null,
            "descrição/Ementa": "autoriza o poder executivo federal a conceder subvenção econômica sob a forma de desconto para liquidação ou renegociação de parcelas de operações de crédito rural de custeio de investimento e de industrialização contratadas por mutuários afetados com perdas materiais decorrentes dos eventos climáticos extremos ocorridos nos meses de abril e maio de 2024 nos termos do decreto legislativo n 36 de 7 de maio de 2024 em municípios do estado do rio grande do sul que tiveram estado de calamidade pública ou situação de emergência reconhecidos pelo poder executivo federal autoriza as instituições financeiras a operarem com mutuários nas condições que especifica altera as leis ns 14042 de 19 de agosto de 2020 8427 de 27 de maio de 1992 14981 de 20 de setembro de 2024 e 13001 de 20 de junho de 2014 e revoga as medidas provisórias ns 1247 de 31 de julho de 2024 e 1272 de 25 de outubro de 2024"
        },
        {
            "documento": "msg 1564/2024  presidência",
            "data": "03/12/2024",
            "autor": "presidência da república",
            "local": "plenário do senado federal",
            "ação legislativa": null,
            "descrição/Ementa": "restitui o autógrafo do projeto de lei n 4448 de 2024 sancionado e convertido na lei n 15038 de 29 de novembro de 2024"
        },
        {
            "documento": "of 1764/2024  casa civil",
            "data": "03/12/2024",
            "autor": "casa civil",
            "local": "plenário do senado federal",
            "ação legislativa": null,
            "descrição/Ementa": "comunica a restituição do autógrafo sancionado e a lei n 15038 de 29 de novembro de 2024 promulgada"
        },
        {
            "documento": "autógrafo restituído após",
            "data": "03/12/2024",
            "autor": "presidência da república",
            "local": "plenário do senado federal",
            "ação legislativa": null,
            "descrição/Ementa": "autógrafo restituído pela presidência da república ao senado federal após sanção"
        },
        {
            "documento": "ofsf 1333/2024",
            "data": "04/12/2024",
            "autor": "primeirosecretário do senado federal",
            "local": "comissão diretora do senado federal",
            "ação legislativa": null,
            "descrição/Ementa": "pg 5 atividade legislativa projeto de lei n 4448 de 2024 documentos 2024 à coarq comunica à câmara dos deputados o recebimento do autógrafo sancionado do projeto de lei n 4448 de 2024"
        }
    ]
}